{
  "schema_version": "1.0",
  "generated_at": "2026-07-22",
  "investigation_scope": {
    "province": "广东省",
    "city": "汕尾市",
    "region": "海丰县",
    "job": "县委书记",
    "task_id": "guangdong_海丰县",
    "time_focus": "2026"
  },
  "identity": {
    "person_id": "haifeng_guo_wenjiong",
    "name": "郭文炯",
    "aliases": [],
    "gender": "男",
    "ethnicity": "汉族",
    "birth": "",
    "birthplace": "",
    "native_place": "",
    "education": [],
    "party_join": "中共党员",
    "work_start": "",
    "dedupe_keys": {
      "name_birth": "郭文炯_",
      "name_birthplace": "郭文炯_",
      "official_profile_url": "http://www.gdhf.gov.cn/gdhf/jjhf/zwdt/content/post_1263405.html"
    }
  },
  "current_status": {
    "current_post": "海丰县委书记",
    "current_org": "中共海丰县委员会",
    "administrative_rank": "正处级",
    "as_of": "2026-07-22",
    "is_current_confirmed": true,
    "source_ids": ["S001", "S002"]
  },
  "career_timeline": [
    {
      "start": "unknown",
      "end": "unknown",
      "org": "履历缺口",
      "title": "",
      "notes": "公开资料未找到郭文炯完整履历。仅确认至2026年7月任海丰县委书记。此前曾任汕尾市有关职务，需进一步查证。",
      "confidence": "unverified",
      "source_ids": []
    }
  ],
  "organizations": [
    {"org_id": 1, "org_name": "中共海丰县委员会"}
  ],
  "relationships": [],
  "governance_record": [
    {
      "period": "2026-07",
      "domain": "other",
      "achievement_or_event": "主持县委常委会研究部署防汛减灾、安全生产、深化改革等工作",
      "role_in_event": "主持",
      "measurable_outcome": "",
      "location": "海丰县",
      "confidence": "confirmed",
      "source_ids": ["S001"]
    },
    {
      "period": "2026-07",
      "domain": "other",
      "achievement_or_event": "主持县委十二届十次全体会议，部署县第十三次党代会筹备工作",
      "role_in_event": "主持",
      "measurable_outcome": "",
      "location": "海丰县",
      "confidence": "confirmed",
      "source_ids": ["S003"]
    },
    {
      "period": "2026-07",
      "domain": "other",
      "achievement_or_event": "陪同市委书记逯峰调研海丰县'百千万工程'推进情况",
      "role_in_event": "陪同调研",
      "measurable_outcome": "",
      "location": "海丰县",
      "confidence": "confirmed",
      "source_ids": ["S004"]
    }
  ],
  "professional_profile": {
    "primary_specializations": [],
    "secondary_specializations": [],
    "career_pattern": "unknown",
    "systems_experience": ["party"],
    "geographic_pattern": [],
    "promotion_velocity": {"summary": "资料不足", "notable_fast_promotions": []}
  },
  "work_style_and_personality": {
    "public_style_indicators": [
      {
        "trait": "unknown",
        "evidence": "资料不足",
        "confidence": "unverified",
        "source_ids": []
      }
    ],
    "speech_themes": [],
    "management_signals": [],
    "caveat": "Work style is inferred from public records, speeches, and reported governance actions, not private psychological assessment."
  },
  "network_metrics": {},
  "risk_and_integrity_signals": [
    {
      "type": "none_found",
      "description": "截至2026年7月，未发现郭文炯相关纪律处分、审计问题或负面报道",
      "date": "",
      "confidence": "plausible",
      "source_ids": []
    }
  ],
  "source_register": [
    {
      "id": "S001",
      "title": "县委常委会召开会议 研究部署防汛减灾、安全生产、深化改革等工作 郭文炯主持会议",
      "url": "http://www.gdhf.gov.cn/gdhf/jjhf/zwdt/content/post_1263405.html",
      "publisher": "海丰县人民政府门户网站",
      "published_at": "2026-07-22",
      "accessed_at": "2026-07-22",
      "source_type": "official",
      "reliability": "high",
      "notes": "Confirmed 郭文炯 as 海丰县委书记"
    },
    {
      "id": "S002",
      "title": "县委常委会召开会议 认真学习贯彻习近平党建思想 郭文炯主持会议",
      "url": "http://www.gdhf.gov.cn/gdhf/jjhf/zwdt/content/post_1261071.html",
      "publisher": "海丰县人民政府门户网站",
      "published_at": "2026-07-10",
      "accessed_at": "2026-07-22",
      "source_type": "official",
      "reliability": "high",
      "notes": "Confirmed 郭文炯 as 海丰县委书记"
    },
    {
      "id": "S003",
      "title": "中共海丰县委十二届十次全体会议召开",
      "url": "http://www.gdhf.gov.cn/gdhf/jjhf/zwdt/content/post_1261072.html",
      "publisher": "海丰县人民政府门户网站",
      "published_at": "2026-07-10",
      "accessed_at": "2026-07-22",
      "source_type": "official",
      "reliability": "high"
    },
    {
      "id": "S004",
      "title": "逯峰到海丰县调研督导百千万工程推进情况",
      "url": "https://www.shanwei.gov.cn/shanwei/zwgk/jcxx/zwdt/zwyw/content/post_1261998.html",
      "publisher": "汕尾市人民政府门户网站",
      "published_at": "2026-07-15",
      "accessed_at": "2026-07-22",
      "source_type": "official",
      "reliability": "high",
      "notes": "Mentions 郭文炯 as 市领导 accompanying the city party secretary"
    }
  ],
  "confidence_summary": {
    "identity": "confirmed",
    "current_role": "confirmed",
    "career_completeness": "thin",
    "relationship_confidence": "low",
    "biggest_gap": "郭文炯完整履历（出生年份、籍贯、教育背景、工作经历）完全缺失。需通过百度百科或任前公示补充。"
  },
  "open_questions": [
    {
      "priority": "critical",
      "question": "郭文炯的出生年份、籍贯、教育背景",
      "why_it_matters": "核心人物身份信息缺失",
      "suggested_queries": ["郭文炯 简历", "郭文炯 海丰 任前公示", "郭文炯 百度百科"],
      "last_attempted": "2026-07-22"
    },
    {
      "priority": "critical",
      "question": "郭文炯的完整仕途履历",
      "why_it_matters": "了解其晋升路径和任职背景",
      "suggested_queries": ["郭文炯 任职经历", "郭文炯 汕尾"],
      "last_attempted": "2026-07-22"
    },
    {
      "priority": "high",
      "question": "郭文炯任海丰县委书记的时间",
      "why_it_matters": "确定其就任时间和前任去向",
      "suggested_queries": ["海丰县委书记 任免 2024"],
      "last_attempted": "2026-07-22"
    }
  ]
}
