{
  "schema_version": "1.0",
  "generated_at": "2026-07-15",
  "investigation_scope": {
    "province": "江西省",
    "city": "宜春市",
    "region": "奉新县",
    "job": "县委书记",
    "task_id": "jiangxi_奉新县",
    "time_focus": "2024-2026"
  },
  "identity": {
    "person_id": "fengxin_huang_weimin",
    "name": "黄为民",
    "aliases": [],
    "gender": "男",
    "ethnicity": "汉族",
    "birth": "1978-01",
    "birthplace": "",
    "native_place": "江西宜丰",
    "education": [
      {
        "period": "unknown",
        "institution": "中专",
        "major": "",
        "degree": "中专",
        "study_type": "full_time",
        "source_ids": ["S001"]
      }
    ],
    "party_join": "1997-05",
    "work_start": "1996-07",
    "dedupe_keys": {
      "name_birth": "黄为民_1978",
      "name_birthplace": "黄为民_江西宜丰",
      "official_profile_url": ""
    }
  },
  "current_status": {
    "current_post": "县委书记",
    "current_org": "中共奉新县委员会",
    "administrative_rank": "县处级正职",
    "as_of": "2026-07-15",
    "is_current_confirmed": true,
    "source_ids": ["S001", "S002"]
  },
  "career_timeline": [
    {"start": "1996-08", "end": "1998-03", "org": "奉新县干垦乡", "title": "工办副主任、团委书记", "level": "科员级", "location": "江西奉新", "system": "government", "rank": "", "is_key_promotion": false, "notes": "", "confidence": "confirmed", "source_ids": ["S001"]},
    {"start": "1998-03", "end": "1999-07", "org": "共青团奉新县委", "title": "副书记", "level": "副科级", "location": "江西奉新", "system": "other", "rank": "", "is_key_promotion": false, "notes": "", "confidence": "confirmed", "source_ids": ["S001"]},
    {"start": "1999-07", "end": "2000-05", "org": "共青团奉新县委", "title": "书记(副科级)", "level": "副科级", "location": "江西奉新", "system": "other", "rank": "", "is_key_promotion": false, "notes": "", "confidence": "confirmed", "source_ids": ["S001"]},
    {"start": "2000-05", "end": "2001-12", "org": "共青团奉新县委", "title": "书记", "level": "正科级", "location": "江西奉新", "system": "other", "rank": "", "is_key_promotion": true, "notes": "由副科转正科", "confidence": "confirmed", "source_ids": ["S001"]},
    {"start": "2001-12", "end": "2002-12", "org": "奉新县上富镇", "title": "党委副书记、纪委书记", "level": "乡科级副职", "location": "江西奉新", "system": "party", "rank": "", "is_key_promotion": false, "notes": "", "confidence": "confirmed", "source_ids": ["S001"]},
    {"start": "2002-12", "end": "2004-01", "org": "奉新县溜头乡", "title": "党委书记、人大主席", "level": "乡科级正职", "location": "江西奉新", "system": "party", "rank": "", "is_key_promotion": true, "notes": "乡镇一把手", "confidence": "confirmed", "source_ids": ["S001"]},
    {"start": "2004-01", "end": "2004-03", "org": "奉新县柳溪乡(溜头乡更名)", "title": "党委书记、人大主席", "level": "乡科级正职", "location": "江西奉新", "system": "party", "rank": "", "is_key_promotion": false, "notes": "乡镇合并更名", "confidence": "confirmed", "source_ids": ["S001"]},
    {"start": "2004-03", "end": "2007-02", "org": "宜丰县花桥乡", "title": "党委书记、人大主席", "level": "乡科级正职", "location": "江西宜丰", "system": "party", "rank": "", "is_key_promotion": false, "notes": "跨县交流", "confidence": "confirmed", "source_ids": ["S001"]},
    {"start": "2007-02", "end": "2009-01", "org": "宜丰县新庄镇", "title": "党委书记", "level": "乡科级正职", "location": "江西宜丰", "system": "party", "rank": "", "is_key_promotion": false, "notes": "", "confidence": "confirmed", "source_ids": ["S001"]},
    {"start": "2009-01", "end": "2009-04", "org": "宜丰县新庄镇", "title": "党委书记、人大主席", "level": "乡科级正职", "location": "江西宜丰", "system": "party", "rank": "", "is_key_promotion": false, "notes": "", "confidence": "confirmed", "source_ids": ["S001"]},
    {"start": "2009-04", "end": "2011-06", "org": "共青团宜春市委", "title": "副书记、党组成员", "level": "县处级副职", "location": "江西宜春", "system": "other", "rank": "", "is_key_promotion": true, "notes": "进入市直副处级", "confidence": "confirmed", "source_ids": ["S001"]},
    {"start": "2011-06", "end": "2013-03", "org": "中共袁州区委", "title": "区委常委、宣传部长", "level": "县处级副职", "location": "江西宜春袁州", "system": "propaganda", "rank": "", "is_key_promotion": true, "notes": "进入区县委常委班子", "confidence": "confirmed", "source_ids": ["S001"]},
    {"start": "2013-03", "end": "2013-06", "org": "中共袁州区委", "title": "区委常委、宣传部长，机电产业基地党委书记", "level": "县处级副职", "location": "江西宜春袁州", "system": "propaganda", "rank": "", "is_key_promotion": false, "notes": "兼产业基地党委书记", "confidence": "confirmed", "source_ids": ["S001"]},
    {"start": "2013-06", "end": "2013-08", "org": "共青团宜春市委", "title": "负责人", "level": "县处级", "location": "江西宜春", "system": "other", "rank": "", "is_key_promotion": false, "notes": "过渡", "confidence": "confirmed", "source_ids": ["S001"]},
    {"start": "2013-08", "end": "2014-01", "org": "共青团宜春市委", "title": "书记、党组书记(副县级)", "level": "县处级副职", "location": "江西宜春", "system": "other", "rank": "", "is_key_promotion": false, "notes": "副县级", "confidence": "confirmed", "source_ids": ["S001"]},
    {"start": "2014-01", "end": "2016-07", "org": "共青团宜春市委", "title": "书记、党组书记", "level": "县处级正职", "location": "江西宜春", "system": "other", "rank": "", "is_key_promotion": true, "notes": "晋升正处级", "confidence": "confirmed", "source_ids": ["S001"]},
    {"start": "2016-07", "end": "2016-10", "org": "铜鼓县", "title": "县委副书记、县长人选", "level": "县处级正职", "location": "江西铜鼓", "system": "government", "rank": "", "is_key_promotion": true, "notes": "从团委转政府主官", "confidence": "confirmed", "source_ids": ["S001"]},
    {"start": "2016-10", "end": "2020-12", "org": "铜鼓县人民政府", "title": "县长", "level": "县处级正职", "location": "江西铜鼓", "system": "government", "rank": "县处级正职", "is_key_promotion": false, "notes": "铜鼓县委副书记、县长", "confidence": "confirmed", "source_ids": ["S001"]},
    {"start": "2020-12", "end": "2021-01", "org": "靖安县", "title": "县委副书记、提名为县长候选人", "level": "县处级正职", "location": "江西靖安", "system": "government", "rank": "", "is_key_promotion": false, "notes": "", "confidence": "confirmed", "source_ids": ["S001"]},
    {"start": "2021-01", "end": "2021-02", "org": "靖安县人民政府", "title": "县委副书记、副县长、代理县长", "level": "县处级正职", "location": "江西靖安", "system": "government", "rank": "", "is_key_promotion": false, "notes": "", "confidence": "confirmed", "source_ids": ["S001"]},
    {"start": "2021-02", "end": "2024-12", "org": "靖安县人民政府", "title": "县长、党组书记", "level": "县处级正职", "location": "江西靖安", "system": "government", "rank": "县处级正职", "is_key_promotion": false, "notes": "靖安县委副书记、县长", "confidence": "confirmed", "source_ids": ["S001"]},
    {"start": "2024-12", "end": "至今", "org": "中共奉新县委员会", "title": "县委书记", "level": "县处级正职", "location": "江西奉新", "system": "party", "rank": "县处级正职", "is_key_promotion": true, "notes": "奉新县委书记（从靖安县长升任县委书记）", "confidence": "confirmed", "source_ids": ["S001", "S002"]}
  ],
  "organizations": [
    {"id": "org_fengxin_committee", "name": "中共奉新县委员会", "role": "current_org", "type": "党委"},
    {"id": "org_fengxin_gov", "name": "奉新县人民政府", "role": "former_org", "type": "政府"},
    {"id": "org_jingan_gov", "name": "靖安县人民政府", "role": "former_org", "type": "政府"},
    {"id": "org_tonggu_gov", "name": "铜鼓县人民政府", "role": "former_org", "type": "政府"},
    {"id": "org_yichun_tuanwei", "name": "共青团宜春市委", "role": "former_org", "type": "群团"}
  ],
  "relationships": [
    {"person": "陈伟", "person_id": "fengxin_chen_wei", "relationship_type": "党政搭档", "strength": "strong", "evidence": "黄为民任县委书记,陈伟任县委副书记、县长候选人(2024.12)", "overlap_org": "中共奉新县委员会", "overlap_period": "2024-12至今", "direction": "undirected", "confidence": "confirmed", "source_ids": ["S001", "S002"]},
    {"person": "陈志尧", "person_id": "fengxin_chen_zhiyao", "relationship_type": "predecessor_successor", "strength": "strong", "evidence": "陈志尧2024年9月调离,黄为民2024年12月接任奉新县委书记", "overlap_org": "中共奉新县委员会", "overlap_period": "2024-09/2024-12", "direction": "undirected", "confidence": "confirmed", "source_ids": ["S001", "S003"]},
    {"person": "喻军", "person_id": "fengxin_yu_jun", "relationship_type": "predecessor_successor", "strength": "medium", "evidence": "黄为民曾任靖安县长(2021-2024),喻军后任靖安县委书记(2024.12);二人在靖安-奉新间交叠", "overlap_org": "靖安县人民政府", "overlap_period": "2021-02/2024-12", "direction": "undirected", "confidence": "confirmed", "source_ids": ["S001"]}
  ],
  "governance_record": [
    {"period": "2016-2020", "domain": "other", "achievement_or_event": "铜鼓县长任内", "role_in_event": "县长", "measurable_outcome": "", "location": "江西铜鼓", "confidence": "unverified", "source_ids": []},
    {"period": "2021-2024", "domain": "other", "achievement_or_event": "靖安县长任内", "role_in_event": "县长", "measurable_outcome": "", "location": "江西靖安", "confidence": "unverified", "source_ids": []}
  ],
  "professional_profile": {
    "primary_specializations": ["基层治理", "共青团工作"],
    "secondary_specializations": [],
    "career_pattern": "local_ladder",
    "systems_experience": ["party", "government", "other"],
    "geographic_pattern": ["奉新", "宜丰", "袁州", "铜鼓", "靖安"],
    "promotion_velocity": {
      "summary": "基层起步(奉新11年), 团委系统6年后转政府主官, 较为稳健",
      "notable_fast_promotions": []
    }
  },
  "work_style_and_personality": {
    "public_style_indicators": [
      {
        "trait": "unknown",
        "evidence": "公开资料不足以推断工作风格",
        "confidence": "unverified",
        "source_ids": []
      }
    ],
    "speech_themes": [],
    "management_signals": [],
    "caveat": "Work style is inferred from public records, speeches, and reported governance actions, not private psychological assessment."
  },
  "network_metrics": {},
  "risk_and_integrity_signals": [
    {
      "type": "none_found",
      "description": "搜索未发现黄为民涉及纪律审查、处分或负面报道",
      "date": "",
      "confidence": "plausible",
      "source_ids": []
    }
  ],
  "source_register": [
    {"id": "S001", "title": "宜丰人黄为民任奉新县委书记！喻军任靖安县委书记", "url": "https://www.163.com/dy/article/JKB05GCC05496YZA.html", "publisher": "网易新闻/会长大叔", "published_at": "2024-12-26", "accessed_at": "2026-07-15", "source_type": "media", "reliability": "high", "notes": "包含黄为民完整人物履历"},
    {"id": "S002", "title": "喻军任靖安县委书记 黄为民任奉新县委书记", "url": "https://www.163.com/dy/article/JK6SE53505500FOQ.html", "publisher": "网易新闻/江西新闻联播", "published_at": "2024-12-24", "accessed_at": "2026-07-15", "source_type": "media", "reliability": "high", "notes": "官方任命发布"},
    {"id": "S003", "title": "陈志尧同志任宜春经济技术开发区管委会主任", "url": "https://www.163.com/dy/article/JBNMDOS805496YZA.html", "publisher": "网易新闻/会长大叔", "published_at": "2024-09-10", "accessed_at": "2026-07-15", "source_type": "media", "reliability": "high", "notes": "陈志尧履历全文"}
  ],
  "confidence_summary": {
    "identity": "confirmed",
    "current_role": "confirmed",
    "career_completeness": "complete",
    "relationship_confidence": "high",
    "biggest_gap": "执政实绩（铜鼓县长、靖安县长期间的具体政绩）评估"
  },
  "open_questions": [
    {
      "priority": "high",
      "question": "黄为民在铜鼓县长、靖安县长期间的执政实绩如何？",
      "why_it_matters": "判断其施政风格和县域治理能力",
      "suggested_queries": ["黄为民 铜鼓 经济发展", "黄为民 靖安 项目"],
      "last_attempted": "2026-07-15"
    },
    {
      "priority": "medium",
      "question": "黄为民的学历细节？仅为中专学历在正处级岗位上较为罕见，是否有后续进修？",
      "why_it_matters": "理解其教育背景和政治成长路径",
      "suggested_queries": ["黄为民 学历 进修 党校"],
      "last_attempted": "2026-07-15"
    }
  ]
}
