{
  "schema_version": "1.0",
  "generated_at": "2026-07-22",
  "investigation_scope": {
    "province": "广东省",
    "city": "韶关市",
    "region": "始兴县",
    "job": "县委书记",
    "task_id": "guangdong_始兴县",
    "time_focus": "2021-2026"
  },
  "identity": {
    "person_id": "shixing_hua_guan",
    "name": "华关",
    "aliases": [],
    "gender": "男",
    "ethnicity": "汉族",
    "birth": "1976年",
    "birthplace": "",
    "native_place": "",
    "education": [
      {
        "period": "",
        "institution": "",
        "major": "",
        "degree": "在职大学学历",
        "study_type": "unknown",
        "source_ids": ["S002"]
      }
    ],
    "party_join": "",
    "work_start": "",
    "dedupe_keys": {
      "name_birth": "华关_1976",
      "name_birthplace": "华关_",
      "official_profile_url": ""
    }
  },
  "current_status": {
    "current_post": "曾任始兴县委书记（2021年—？）",
    "current_org": "中共始兴县委员会",
    "administrative_rank": "县处级正职",
    "as_of": "2026年7月（在任不明）",
    "is_current_confirmed": false,
    "source_ids": ["S001", "S002"]
  },
  "career_timeline": [
    {
      "start": "unknown",
      "end": "unknown",
      "org": "履历缺口",
      "title": "",
      "notes": "华关的早期履历因网络搜索受限无法获取。已知他在任始兴县委书记前曾担任始兴县长。",
      "confidence": "unverified",
      "source_ids": []
    },
    {
      "start": "unknown",
      "end": "2021年",
      "org": "始兴县人民政府",
      "title": "县长",
      "level": "县处级正职",
      "location": "广东省韶关市始兴县",
      "system": "government",
      "rank": "",
      "is_key_promotion": true,
      "notes": "华关任始兴县长后升任县委书记",
      "confidence": "plausible",
      "source_ids": ["S002"]
    },
    {
      "start": "2021年",
      "end": "unknown",
      "org": "中共始兴县委员会",
      "title": "县委书记",
      "level": "县处级正职",
      "location": "广东省韶关市始兴县",
      "system": "party",
      "rank": "",
      "is_key_promotion": true,
      "notes": "华关接替黄令遥担任始兴县委书记",
      "confidence": "plausible",
      "source_ids": ["S001", "S002"]
    }
  ],
  "organizations": [],
  "relationships": [
    {
      "person": "黄令遥",
      "person_id": "shixing_huang_lingyao",
      "relationship_type": "predecessor_successor",
      "strength": "strong",
      "evidence": "华关接替黄令遥担任始兴县委书记（2021年）",
      "overlap_org": "中共始兴县委员会",
      "overlap_period": "2021年",
      "direction": "other_to_person",
      "confidence": "confirmed",
      "source_ids": ["S001"]
    },
    {
      "person": "叶洪番",
      "person_id": "shixing_ye_hongfan",
      "relationship_type": "predecessor_successor",
      "strength": "strong",
      "evidence": "华关接替叶洪番担任始兴县长",
      "overlap_org": "始兴县人民政府",
      "overlap_period": "待查",
      "direction": "other_to_person",
      "confidence": "plausible",
      "source_ids": ["S002"]
    }
  ],
  "governance_record": [],
  "professional_profile": {
    "primary_specializations": [],
    "secondary_specializations": [],
    "career_pattern": "local_ladder",
    "systems_experience": ["government", "party"],
    "geographic_pattern": [],
    "promotion_velocity": {
      "summary": "信息不足无法评估。华关由县长晋升县委书记，属于县级正常晋升路径。",
      "notable_fast_promotions": []
    }
  },
  "work_style_and_personality": {
    "public_style_indicators": [],
    "speech_themes": [],
    "management_signals": [],
    "caveat": "Work style is inferred from public records, speeches, and reported governance actions, not private psychological assessment."
  },
  "network_metrics": {},
  "risk_and_integrity_signals": [
    {
      "type": "none_found",
      "description": "搜索范围内未发现华关的纪律处分、审计问题或负面报道",
      "date": "",
      "confidence": "unverified",
      "source_ids": []
    }
  ],
  "source_register": [
    {
      "id": "S001",
      "title": "始兴县 - 维基百科",
      "url": "https://zh.wikipedia.org/wiki/始兴县",
      "publisher": "维基百科",
      "published_at": "",
      "accessed_at": "2026-07-22",
      "source_type": "encyclopedia",
      "reliability": "medium",
      "notes": "维基百科始兴县词条列出历任信息"
    },
    {
      "id": "S002",
      "title": "公开新闻报道",
      "url": "",
      "publisher": "综合新闻来源",
      "published_at": "",
      "accessed_at": "2026-07-22",
      "source_type": "media",
      "reliability": "medium",
      "notes": "华关任始兴县委书记、此前任始兴县长的多条新闻报道"
    }
  ],
  "confidence_summary": {
    "identity": "plausible",
    "current_role": "plausible",
    "career_completeness": "thin",
    "relationship_confidence": "medium",
    "biggest_gap": "华关的完整履历（出生地、教育、早期任职）全部待查"
  },
  "open_questions": [
    {
      "priority": "critical",
      "question": "华关的出生地、籍贯和完整教育背景是什么？",
      "why_it_matters": "无法建立完整身份档案和关系网络",
      "suggested_queries": ["华关 简历 始兴", "华关 出生", "华关 百度百科"],
      "last_attempted": "2026-07-22"
    },
    {
      "priority": "critical",
      "question": "华关任始兴县长之前的早期履历？",
      "why_it_matters": "无法评估其仕途轨迹和潜力",
      "suggested_queries": ["华关 任职经历", "华关 此前 担任"],
      "last_attempted": "2026-07-22"
    },
    {
      "priority": "high",
      "question": "华关在2024年后是否仍在始兴县委书记任上，还是已调任？",
      "why_it_matters": "需要确认当前在任者",
      "suggested_queries": ["华关 始兴县委书记 2024", "始兴县 县委书记 2025"],
      "last_attempted": "2026-07-22"
    }
  ]
}
