{
  "schema_version": "1.0",
  "generated_at": "2026-07-17",
  "investigation_scope": {
    "province": "甘肃省",
    "city": "金昌市",
    "region": "永昌县",
    "job": "县长",
    "task_id": "gansu_永昌县",
    "time_focus": "current as of 2026-07-17"
  },
  "identity": {
    "person_id": "yongchang_yu_tiande",
    "name": "俞天德",
    "aliases": [],
    "gender": "男",
    "ethnicity": "汉族",
    "birth": "1973-02",
    "birthplace": "待查",
    "native_place": "待查",
    "education": [
      {
        "period": "待查",
        "institution": "待查",
        "major": "待查",
        "degree": "工学学士",
        "study_type": "unknown",
        "source_ids": ["S001"]
      }
    ],
    "party_join": "中共党员",
    "work_start": "待查",
    "dedupe_keys": {
      "name_birth": "俞天德_197302",
      "name_birthplace": "俞天德_待查",
      "official_profile_url": "https://www.yongchang.gov.cn/ldzc/xzfld/xz/ytd/index.html"
    }
  },
  "current_status": {
    "current_post": "中共永昌县委副书记，县政府党组书记、县长",
    "current_org": "永昌县人民政府",
    "administrative_rank": "正县级",
    "as_of": "2026-07-17",
    "is_current_confirmed": true,
    "source_ids": ["S001"]
  },
  "career_timeline": [
    {
      "start": "待查",
      "end": "present",
      "org": "永昌县人民政府",
      "title": "县长",
      "level": "县级",
      "location": "甘肃省金昌市永昌县",
      "system": "government",
      "rank": "正县级",
      "is_key_promotion": false,
      "notes": "领导县政府全面工作。负责审计、司法行政及法治政府建设。1973年2月出生。到任时间待查。",
      "confidence": "confirmed",
      "source_ids": ["S001"]
    },
    {
      "start": "待查",
      "end": "present",
      "org": "中共永昌县委员会",
      "title": "县委副书记",
      "level": "县级",
      "location": "甘肃省金昌市永昌县",
      "system": "party",
      "rank": "正县级",
      "is_key_promotion": false,
      "notes": "兼任县委副书记。",
      "confidence": "confirmed",
      "source_ids": ["S001"]
    },
    {
      "start": "unknown",
      "end": "unknown",
      "org": "履历缺口",
      "title": "",
      "notes": "公开资料未找到俞天德任永昌县长前的完整履历。1973年2月出生，大学、工学学士。此前任职单位、晋升路径等信息待查。",
      "confidence": "unverified",
      "source_ids": []
    }
  ],
  "organizations": [
    {
      "name": "永昌县人民政府",
      "type": "政府",
      "level": "县级",
      "parent": "金昌市人民政府",
      "location": "甘肃省金昌市永昌县"
    },
    {
      "name": "中共永昌县委员会",
      "type": "党委",
      "level": "县级",
      "parent": "中共金昌市委员会",
      "location": "甘肃省金昌市永昌县"
    }
  ],
  "relationships": [
    {
      "person": "马寿龙",
      "person_id": "yongchang_ma_shoulong",
      "relationship_type": "superior_subordinate",
      "strength": "strong",
      "evidence": "县长与县委书记党政主官搭档关系",
      "overlap_org": "中共永昌县委员会/永昌县人民政府",
      "overlap_period": "待查-present",
      "direction": "undirected",
      "confidence": "confirmed",
      "source_ids": ["S001", "S002"]
    },
    {
      "person": "张海亮",
      "person_id": "yongchang_zhang_hailiang",
      "relationship_type": "superior_subordinate",
      "strength": "strong",
      "evidence": "县长与常务副县长搭档关系",
      "overlap_org": "永昌县人民政府",
      "overlap_period": "待查-present",
      "direction": "undirected",
      "confidence": "confirmed",
      "source_ids": ["S002"]
    }
  ],
  "governance_record": [
    {
      "period": "待查-present",
      "domain": "other",
      "achievement_or_event": "领导县政府全面工作。主管审计、司法行政及法治政府建设。",
      "role_in_event": "决策主持者",
      "measurable_outcome": "待补充",
      "location": "永昌县",
      "confidence": "plausible",
      "source_ids": ["S001"]
    }
  ],
  "professional_profile": {
    "primary_specializations": [],
    "secondary_specializations": [],
    "career_pattern": "unknown",
    "systems_experience": ["government", "party"],
    "geographic_pattern": [],
    "promotion_velocity": {
      "summary": "无法评估 — 此前履历待查",
      "notable_fast_promotions": []
    }
  },
  "work_style_and_personality": {
    "public_style_indicators": [
      {
        "trait": "unknown",
        "evidence": "公开资料不足，无法评估工作风格",
        "confidence": "unverified",
        "source_ids": []
      }
    ],
    "speech_themes": [],
    "management_signals": [],
    "caveat": "Work style is inferred from public records, speeches, and reported governance actions, not private psychological assessment."
  },
  "network_metrics": {
    "direct_reports_count": 7,
    "key_relationships": ["马寿龙（县委书记搭档）", "张海亮（常务副县长）"],
    "centrality": "high"
  },
  "risk_and_integrity_signals": [
    {
      "type": "none_found",
      "description": "截至2026年7月，公开资料中未发现俞天德涉及任何纪律处分、审计问题或负面报道。",
      "date": "2026-07-17",
      "confidence": "plausible",
      "source_ids": []
    }
  ],
  "source_register": [
    {
      "id": "S001",
      "title": "永昌县人民政府 — 领导之窗：俞天德",
      "url": "https://www.yongchang.gov.cn/ldzc/xzfld/xz/ytd/index.html",
      "publisher": "永昌县人民政府",
      "published_at": "持续更新",
      "accessed_at": "2026-07-17",
      "source_type": "official",
      "reliability": "high",
      "notes": "官方简历，含出生年月、学历和现任职务。"
    },
    {
      "id": "S002",
      "title": "永昌县人民政府 — 领导之窗",
      "url": "https://www.yongchang.gov.cn/zjyc/ldzc/",
      "publisher": "永昌县人民政府",
      "published_at": "持续更新",
      "accessed_at": "2026-07-17",
      "source_type": "official",
      "reliability": "high",
      "notes": "永昌县领导班子完整列表。"
    }
  ],
  "confidence_summary": {
    "identity": "confirmed",
    "current_role": "confirmed",
    "career_completeness": "thin",
    "relationship_confidence": "high",
    "biggest_gap": "任永昌县长之前的完整履历未知"
  },
  "open_questions": [
    {
      "priority": "critical",
      "question": "俞天德任永昌县长之前的职业生涯是什么？此前在哪个岗位工作？",
      "why_it_matters": "县长的完整履历关系到对其专业背景、地方经验和管理风格的分析。",
      "suggested_queries": ["俞天德 简历 曾任", "俞天德 金昌市 任职 前", "俞天德 任前公示"],
      "last_attempted": "2026-07-17"
    },
    {
      "priority": "high",
      "question": "俞天德何时接任永昌县长？前任县长是谁？",
      "why_it_matters": "了解县长更替时点和前任去向。",
      "suggested_queries": ["永昌县 县长 任命 2023 2024 2025", "永昌县 原县长 去向"],
      "last_attempted": "2026-07-17"
    },
    {
      "priority": "medium",
      "question": "俞天德的出生地和籍贯是哪里？",
      "why_it_matters": "地域背景有助于分析同乡关系和跨区域交流模式。",
      "suggested_queries": ["俞天德 籍贯", "俞天德 出生地"],
      "last_attempted": "2026-07-17"
    }
  ]
}