{
  "schema_version": "1.0",
  "generated_at": "2026-07-15",
  "investigation_scope": {
    "province": "安徽省",
    "city": "淮北市",
    "region": "杜集区",
    "job": "区委书记",
    "task_id": "anhui_杜集区",
    "time_focus": "current (2026)"
  },
  "identity": {
    "person_id": "anhui_huaibei_duji_zhengxiaojun",
    "name": "郑晓军",
    "aliases": [],
    "gender": "男",
    "ethnicity": "汉族",
    "birth": "",
    "birthplace": "",
    "native_place": "",
    "education": [],
    "party_join": "中共党员",
    "work_start": "",
    "dedupe_keys": {
      "name_birth": "郑晓军_",
      "name_birthplace": "郑晓军_",
      "official_profile_url": "https://www.hbdj.gov.cn/"
    }
  },
  "current_status": {
    "current_post": "杜集区委书记、区人武部党委第一书记",
    "current_org": "中共杜集区委员会",
    "administrative_rank": "县处级正职",
    "as_of": "2026-07-15",
    "is_current_confirmed": true,
    "source_ids": ["S001", "S002", "S003"]
  },
  "career_timeline": [
    {
      "start": "unknown",
      "end": "unknown",
      "org": "杜集区人民政府",
      "title": "杜集区区长",
      "level": "县处级正职",
      "location": "安徽省淮北市杜集区",
      "system": "government",
      "rank": "县处级正职",
      "is_key_promotion": false,
      "notes": "推测：郑晓军在2026年6月任区委书记前应为区长。详尽的任职时间线待补充。",
      "confidence": "plausible",
      "source_ids": ["S005"]
    },
    {
      "start": "2026-06",
      "end": "present",
      "org": "中共杜集区委员会",
      "title": "杜集区委书记、区人武部党委第一书记",
      "level": "县处级正职",
      "location": "安徽省淮北市杜集区",
      "system": "party",
      "rank": "县处级正职",
      "is_key_promotion": true,
      "notes": "2026年6月26日当选中共杜集区第九届委员会书记。2026年6月5日任区人武部党委第一书记。",
      "confidence": "confirmed",
      "source_ids": ["S001", "S002"]
    }
  ],
  "organizations": [
    {
      "name": "中共杜集区委员会",
      "type": "党委",
      "level": "县处级",
      "location": "安徽省淮北市杜集区"
    },
    {
      "name": "杜集区人民政府",
      "type": "政府",
      "level": "县处级",
      "location": "安徽省淮北市杜集区"
    },
    {
      "name": "杜集区人民武装部",
      "type": "政府",
      "level": "县处级",
      "location": "安徽省淮北市杜集区"
    }
  ],
  "relationships": [
    {
      "person": "魏辉",
      "person_id": "anhui_huaibei_duji_weihui",
      "relationship_type": "superior_subordinate",
      "strength": "strong",
      "evidence": "区委书记与区长，区委领导班子正副搭档，共同当选九届区委常委、委员",
      "overlap_org": "中共杜集区委员会",
      "overlap_period": "2026-06至今",
      "direction": "person_to_other",
      "confidence": "confirmed",
      "source_ids": ["S001"]
    },
    {
      "person": "魏宾",
      "person_id": "anhui_huaibei_duji_weibin",
      "relationship_type": "superior_subordinate",
      "strength": "strong",
      "evidence": "区委书记与区委副书记，共同当选九届区委领导班子成员",
      "overlap_org": "中共杜集区委员会",
      "overlap_period": "2026-06至今",
      "direction": "person_to_other",
      "confidence": "confirmed",
      "source_ids": ["S001"]
    },
    {
      "person": "徐善鲲",
      "person_id": "anhui_huaibei_duji_xushankun",
      "relationship_type": "superior_subordinate",
      "strength": "medium",
      "evidence": "区委常委徐善鲲于2026年6月11日陪同郑晓军赴杜集经开区督导调研",
      "overlap_org": "中共杜集区委员会",
      "overlap_period": "2026-06至今",
      "direction": "person_to_other",
      "confidence": "confirmed",
      "source_ids": ["S003"]
    },
    {
      "person": "许家升",
      "person_id": "anhui_huaibei_duji_xujiasheng",
      "relationship_type": "superior_subordinate",
      "strength": "medium",
      "evidence": "郑晓军任区人武部党委第一书记，许家升任人武部上校政治委员",
      "overlap_org": "杜集区人民武装部",
      "overlap_period": "2026-06至今",
      "direction": "person_to_other",
      "confidence": "confirmed",
      "source_ids": ["S002"]
    }
  ],
  "governance_record": [
    {
      "period": "2026-06",
      "domain": "economic_development",
      "achievement_or_event": "赴杜集经开区督导调研，要求扛起发展之责，做大园区体量做优质量",
      "role_in_event": "区委书记，调研指导",
      "measurable_outcome": "",
      "location": "淮北市杜集区",
      "confidence": "confirmed",
      "source_ids": ["S003"]
    },
    {
      "period": "2026-06",
      "domain": "urban_construction",
      "achievement_or_event": "任区人武部党委第一书记，强调党管武装、军民融合",
      "role_in_event": "区委书记、人武部党委第一书记",
      "measurable_outcome": "",
      "location": "淮北市杜集区",
      "confidence": "confirmed",
      "source_ids": ["S002"]
    },
    {
      "period": "2026-06",
      "domain": "other",
      "achievement_or_event": "主持区第九次党代会作报告，提出打造'产业转型样板区、省际合作实验区、矿区蝶变示范区'",
      "role_in_event": "区委书记，作区委工作报告",
      "measurable_outcome": "提出今后五年发展目标",
      "location": "淮北市杜集区",
      "confidence": "confirmed",
      "source_ids": ["S004"]
    },
    {
      "period": "2026-06",
      "domain": "discipline",
      "achievement_or_event": "开展树立和践行正确政绩观学习教育，结合省委巡视抓好问题整改",
      "role_in_event": "区委书记",
      "measurable_outcome": "",
      "location": "淮北市杜集区",
      "confidence": "confirmed",
      "source_ids": ["S003"]
    }
  ],
  "professional_profile": {
    "primary_specializations": ["地方治理", "党建", "经济开发区管理"],
    "secondary_specializations": [],
    "career_pattern": "local_ladder",
    "systems_experience": ["party", "government", "military_area"],
    "geographic_pattern": ["安徽省", "淮北市"],
    "promotion_velocity": {
      "summary": "从区长晋升区委书记，晋升时间线待补充完整评估",
      "notable_fast_promotions": []
    }
  },
  "work_style_and_personality": {
    "public_style_indicators": [
      {
        "trait": "pragmatic",
        "evidence": "调研中强调'用效果交账、用实绩说话'，要求'懂产业趋势、懂政策工具、懂市场规律'",
        "confidence": "confirmed",
        "source_ids": ["S003"]
      },
      {
        "trait": "discipline_oriented",
        "evidence": "多次强调全面从严治党、纪律作风、正确政绩观、巡视整改",
        "confidence": "confirmed",
        "source_ids": ["S003", "S006"]
      },
      {
        "trait": "reform_oriented",
        "evidence": "提出'产业转型样板区、省际合作实验区、矿区蝶变示范区'三区战略定位",
        "confidence": "confirmed",
        "source_ids": ["S004"]
      }
    ],
    "speech_themes": ["高质量发展", "产业转型", "全面从严治党", "改革创新"],
    "management_signals": [
      "强调'班子强则开发区兴'，注重干部专业能力建设",
      "要求'让有为者有位、能干者能上'"
    ],
    "caveat": "Work style is inferred from public records, speeches, and reported governance actions, not private psychological assessment."
  },
  "network_metrics": {
    "centrality": "high",
    "role": "core_leader",
    "direct_reports": 10,
    "peer_count": 1,
    "subordinate_count": 9
  },
  "risk_and_integrity_signals": [
    {
      "type": "none_found",
      "description": "截至2026年7月15日，未发现郑晓军相关的纪律处分、负面舆情或异常调离信号",
      "date": "2026-07-15",
      "confidence": "plausible",
      "source_ids": []
    }
  ],
  "source_register": [
    {
      "id": "S001",
      "title": "中国共产党淮北市杜集区第九届委员会举行第一次全体会议",
      "url": "https://www.hbdj.gov.cn/xwzx/djyw/60923792.html",
      "publisher": "杜集区人民政府",
      "published_at": "2026-06-27",
      "accessed_at": "2026-07-15",
      "source_type": "official",
      "reliability": "high",
      "notes": "九届一次全会选举结果，确认区委常委、书记、副书记名单"
    },
    {
      "id": "S002",
      "title": "杜集区人武部召开党委第一书记任职通知大会",
      "url": "https://www.hbdj.gov.cn/xwzx/djyw/60923025.html",
      "publisher": "杜集区人民政府",
      "published_at": "2026-06-05",
      "accessed_at": "2026-07-15",
      "source_type": "official",
      "reliability": "high",
      "notes": "郑晓军任区人武部党委第一书记"
    },
    {
      "id": "S003",
      "title": "区委书记郑晓军赴杜集经开区督导调研",
      "url": "https://www.hbdj.gov.cn/xwzx/djyw/60923275.html",
      "publisher": "杜集区人民政府",
      "published_at": "2026-06-12",
      "accessed_at": "2026-07-15",
      "source_type": "official",
      "reliability": "high",
      "notes": "郑晓军调研讲话，与徐善鲲陪同"
    },
    {
      "id": "S004",
      "title": "中国共产党淮北市杜集区第九次代表大会隆重开幕",
      "url": "https://www.hbdj.gov.cn/xwzx/djyw/60923763.html",
      "publisher": "杜集区人民政府",
      "published_at": "2026-06-26",
      "accessed_at": "2026-07-15",
      "source_type": "official",
      "reliability": "high",
      "notes": "郑晓军作区委工作报告，魏辉主持大会"
    },
    {
      "id": "S005",
      "title": "推断：区委书记通常由区长晋升",
      "url": "",
      "publisher": "",
      "published_at": "",
      "accessed_at": "2026-07-15",
      "source_type": "inferred",
      "reliability": "low",
      "notes": "郑晓军在任书记前的职务未从公开报道直接确认，推断为区长晋升"
    },
    {
      "id": "S006",
      "title": "杜集区召开'两优一先'表彰大会",
      "url": "https://www.hbdj.gov.cn/xwzx/djyw/60924123.html",
      "publisher": "杜集区人民政府",
      "published_at": "2026-07-02",
      "accessed_at": "2026-07-15",
      "source_type": "official",
      "reliability": "high",
      "notes": "郑晓军出席表彰大会并讲话"
    },
    {
      "id": "S007",
      "title": "淮北师范大学赴杜集区调研暑期'三下乡'社会实践座谈交流会在石台镇召开",
      "url": "https://www.hbdj.gov.cn/xwzx/djyw/60924372.html",
      "publisher": "杜集区人民政府",
      "published_at": "2026-07-14",
      "accessed_at": "2026-07-15",
      "source_type": "official",
      "reliability": "high",
      "notes": "郑晓军与淮北师范大学座谈，魏宾主持会议"
    }
  ],
  "confidence_summary": {
    "identity": "confirmed",
    "current_role": "confirmed",
    "career_completeness": "thin",
    "relationship_confidence": "medium",
    "biggest_gap": "郑晓军任区委书记前的完整履历未知（出生年份、籍贯、教育背景、职务晋升时间线）"
  },
  "open_questions": [
    {
      "priority": "critical",
      "question": "郑晓军的出生年份、籍贯、教育背景是什么？",
      "why_it_matters": "人物身份确认和去重关键信息",
      "suggested_queries": ["郑晓军 杜集区 简历", "郑晓军 出生", "郑晓军 安徽"],
      "last_attempted": "2026-07-15"
    },
    {
      "priority": "critical",
      "question": "郑晓军任区委书记前的完整履历（此前是否任区长？何时开始任区长？之前的职务？）",
      "why_it_matters": "完整的职业晋升链对关系网络分析至关重要",
      "suggested_queries": ["郑晓军 杜集区 区长", "郑晓军 任职"],
      "last_attempted": "2026-07-15"
    },
    {
      "priority": "high",
      "question": "郑晓军的入党时间和参加工作时间",
      "why_it_matters": "党龄和工作年限信息",
      "suggested_queries": ["郑晓军 入党"],
      "last_attempted": "2026-07-15"
    },
    {
      "priority": "medium",
      "question": "郑晓军的前任杜集区委书记是谁？去向如何？",
      "why_it_matters": "分析换届和继任模式",
      "suggested_queries": ["杜集区 前任 区委书记"],
      "last_attempted": "2026-07-15"
    }
  ]
}
