{
  "schema_version": "1.0",
  "generated_at": "2026-07-17",
  "investigation_scope": {
    "province": "福建省",
    "city": "龙岩市",
    "region": "连城县",
    "job": "县政府党组成员、冠豸山风景区管委会党委书记",
    "task_id": "fujian_连城县",
    "time_focus": "2026-07-17"
  },
  "identity": {
    "person_id": "fujian_longyan_liancheng_李川龙",
    "name": "李川龙",
    "aliases": [],
    "gender": "男",
    "ethnicity": "汉族",
    "birth": "1976-12",
    "birthplace": "",
    "native_place": "",
    "education": [
      {
        "period": "",
        "institution": "",
        "major": "",
        "degree": "研究生",
        "study_type": "full_time",
        "source_ids": [
          "S001"
        ]
      }
    ],
    "party_join": "中共党员",
    "work_start": "",
    "dedupe_keys": {
      "name_birth": "李川龙_1976-12",
      "name_birthplace": "李川龙_",
      "official_profile_url": "http://www.fjlylc.gov.cn/xxgk/ldzc/dzcy/lcl/"
    }
  },
  "current_status": {
    "current_post": "县政府党组成员、冠豸山风景区管委会党委书记",
    "current_org": "连城县人民政府",
    "administrative_rank": "",
    "as_of": "2026-07-17",
    "is_current_confirmed": true,
    "source_ids": [
      "S001"
    ]
  },
  "career_timeline": [
    {
      "start": "",
      "end": "present",
      "org": "连城县人民政府",
      "title": "县政府党组成员",
      "level": "副处级",
      "location": "福建省龙岩市连城县",
      "system": "government",
      "rank": "副处级",
      "is_key_promotion": false,
      "notes": "",
      "confidence": "confirmed",
      "source_ids": [
        "S001"
      ]
    },
    {
      "start": "",
      "end": "present",
      "org": "冠豸山风景区管委会",
      "title": "党委书记",
      "level": "正处级",
      "location": "福建省龙岩市连城县",
      "system": "other",
      "rank": "正处级",
      "is_key_promotion": true,
      "notes": "负责文化、体育、旅游、客家美食工作",
      "confidence": "confirmed",
      "source_ids": [
        "S001"
      ]
    }
  ],
  "organizations": [],
  "relationships": [],
  "governance_record": [],
  "professional_profile": {
    "primary_specializations": [],
    "secondary_specializations": [],
    "career_pattern": "unknown",
    "systems_experience": [],
    "geographic_pattern": [],
    "promotion_velocity": {
      "summary": "",
      "notable_fast_promotions": []
    }
  },
  "work_style_and_personality": {
    "public_style_indicators": [],
    "speech_themes": [],
    "management_signals": [],
    "caveat": "Work style is inferred from public records, speeches, and reported governance actions, not private psychological assessment."
  },
  "network_metrics": {},
  "risk_and_integrity_signals": [
    {
      "type": "none_found",
      "description": "No negative signals found in public records",
      "date": "",
      "confidence": "unverified",
      "source_ids": [
        "S001"
      ]
    }
  ],
  "source_register": [
    {
      "id": "S001",
      "title": "李川龙-连城县人民政府",
      "url": "http://www.fjlylc.gov.cn/xxgk/ldzc/dzcy/lcl/",
      "publisher": "连城县人民政府",
      "published_at": "",
      "accessed_at": "2026-07-17",
      "source_type": "official",
      "reliability": "high",
      "notes": "Confirmed: 1976-12, 男, 汉族, 研究生, 中共党员"
    }
  ],
  "confidence_summary": {
    "identity": "partial",
    "current_role": "confirmed",
    "career_completeness": "thin",
    "relationship_confidence": "medium",
    "biggest_gap": "Detailed career timeline for 李川龙 before current role is unknown"
  },
  "open_questions": [
    {
      "priority": "high",
      "question": "李川龙在担任现职前的详细履历",
      "why_it_matters": "需要完整履历以构建关系网络",
      "suggested_queries": [
        "李川龙 简历",
        "李川龙 任职经历"
      ],
      "last_attempted": "2026-07-17"
    },
    {
      "priority": "medium",
      "question": "李川龙的教育背景和出生地",
      "why_it_matters": "用于身份去重和背景分析",
      "suggested_queries": [
        "李川龙 出生 学历"
      ],
      "last_attempted": "2026-07-17"
    }
  ]
}